{
  "motif": 1,
  "pressure": 1000.0,
  "fem_mesh": "/home/chaoyu/phd_simulation/FDM/../data/B5_remeshed_shared.off",
  "target_crown_m": 0.23167445,
  "converged": true,
  "loss_rmse_m": 0.006265889176176278,
  "n_calls": 477,
  "regions": [
    {
      "region_id": 0,
      "row": 0,
      "col": 0,
      "knit_dir_deg": 0,
      "sf_wale": 1.0992105061076622,
      "sf_course": 1.0478986544686282
    },
    {
      "region_id": 1,
      "row": 0,
      "col": 1,
      "knit_dir_deg": 0,
      "sf_wale": 1.1379305536182625,
      "sf_course": 0.9774954236432736
    },
    {
      "region_id": 2,
      "row": 0,
      "col": 2,
      "knit_dir_deg": 0,
      "sf_wale": 1.0611754018292598,
      "sf_course": 1.0195961664028428
    },
    {
      "region_id": 3,
      "row": 1,
      "col": 0,
      "knit_dir_deg": 0,
      "sf_wale": 1.0802576576193461,
      "sf_course": 1.0919606989976722
    },
    {
      "region_id": 4,
      "row": 1,
      "col": 1,
      "knit_dir_deg": 0,
      "sf_wale": 1.0865872690736251,
      "sf_course": 0.988563595050619
    },
    {
      "region_id": 5,
      "row": 1,
      "col": 2,
      "knit_dir_deg": 0,
      "sf_wale": 1.0590601548546685,
      "sf_course": 1.031555500834439
    },
    {
      "region_id": 6,
      "row": 2,
      "col": 0,
      "knit_dir_deg": 0,
      "sf_wale": 1.1033494545191007,
      "sf_course": 1.0598437906910927
    },
    {
      "region_id": 7,
      "row": 2,
      "col": 1,
      "knit_dir_deg": 0,
      "sf_wale": 1.1365584472213828,
      "sf_course": 1.0274544080087922
    },
    {
      "region_id": 8,
      "row": 2,
      "col": 2,
      "knit_dir_deg": 0,
      "sf_wale": 1.0798284373340763,
      "sf_course": 1.0418752193778098
    }
  ],
  "history": [
    {
      "call": 447,
      "loss": 0.0061511336008799366,
      "crown_height": 0.22424082
    },
    {
      "call": 448,
      "loss": 0.0062551813653197764,
      "crown_height": 0.22428178
    },
    {
      "call": 449,
      "loss": 0.006323806152740016,
      "crown_height": 0.2236824
    },
    {
      "call": 450,
      "loss": 0.006497250200411354,
      "crown_height": 0.22522122
    },
    {
      "call": 451,
      "loss": 0.00626290090274191,
      "crown_height": 0.22386204
    },
    {
      "call": 452,
      "loss": 0.0062895428956480795,
      "crown_height": 0.22397046
    },
    {
      "call": 453,
      "loss": 0.006472878705456293,
      "crown_height": 0.22064261
    },
    {
      "call": 454,
      "loss": 0.00629722959774769,
      "crown_height": 0.22373957
    },
    {
      "call": 455,
      "loss": 0.006435466351562386,
      "crown_height": 0.22360726
    },
    {
      "call": 456,
      "loss": 0.006495367586073004,
      "crown_height": 0.22332733
    },
    {
      "call": 457,
      "loss": 0.006388927382244877,
      "crown_height": 0.22337541
    },
    {
      "call": 458,
      "loss": 0.006265889176176278,
      "crown_height": 0.22513598
    },
    {
      "call": 459,
      "loss": 0.006180871272207206,
      "crown_height": 0.22433905
    },
    {
      "call": 460,
      "loss": 0.006264608934190185,
      "crown_height": 0.22395988
    },
    {
      "call": 461,
      "loss": 0.006193115688121653,
      "crown_height": 0.22454475
    },
    {
      "call": 462,
      "loss": 0.0062764032012414496,
      "crown_height": 0.22471322
    },
    {
      "call": 463,
      "loss": 0.006250381574501362,
      "crown_height": 0.22242509
    },
    {
      "call": 464,
      "loss": 0.006194553732564817,
      "crown_height": 0.22543303
    },
    {
      "call": 465,
      "loss": 0.006208167935689521,
      "crown_height": 0.22430793
    },
    {
      "call": 466,
      "loss": 0.006151133609087165,
      "crown_height": 0.22424082
    },
    {
      "call": 467,
      "loss": 0.0062551813653197764,
      "crown_height": 0.22428178
    },
    {
      "call": 468,
      "loss": 0.006323806152740016,
      "crown_height": 0.2236824
    },
    {
      "call": 469,
      "loss": 0.006497250200411354,
      "crown_height": 0.22522122
    },
    {
      "call": 470,
      "loss": 0.00626290090274191,
      "crown_height": 0.22386204
    },
    {
      "call": 471,
      "loss": 0.0062895428956480795,
      "crown_height": 0.22397046
    },
    {
      "call": 472,
      "loss": 0.006472878705456293,
      "crown_height": 0.22064261
    },
    {
      "call": 473,
      "loss": 0.006297229605170144,
      "crown_height": 0.22373957
    },
    {
      "call": 474,
      "loss": 0.006435466343129692,
      "crown_height": 0.22360726
    },
    {
      "call": 475,
      "loss": 0.006495367586073004,
      "crown_height": 0.22332733
    },
    {
      "call": 476,
      "loss": 0.006388927382244877,
      "crown_height": 0.22337541
    }
  ]
}