{
  "motif": 1,
  "pressure": 1000.0,
  "fem_mesh": "/home/chaoyu/phd_simulation/FDM/../data/B5_remeshed_shared.off",
  "target_crown_m": 0.23167445,
  "converged": true,
  "loss_rmse_m": 0.006450315092961335,
  "n_calls": 622,
  "regions": [
    {
      "region_id": 0,
      "row": 0,
      "col": 0,
      "knit_dir_deg": 0,
      "sf_wale": 1.0414608355553074,
      "sf_course": 1.0424798453424233
    },
    {
      "region_id": 1,
      "row": 0,
      "col": 1,
      "knit_dir_deg": 0,
      "sf_wale": 1.0412011105806913,
      "sf_course": 1.0395930528169672
    },
    {
      "region_id": 2,
      "row": 0,
      "col": 2,
      "knit_dir_deg": 0,
      "sf_wale": 1.0410815678812226,
      "sf_course": 1.0409435253510406
    },
    {
      "region_id": 3,
      "row": 1,
      "col": 0,
      "knit_dir_deg": 0,
      "sf_wale": 1.0421244929888487,
      "sf_course": 1.0417375417356245
    },
    {
      "region_id": 4,
      "row": 1,
      "col": 1,
      "knit_dir_deg": 0,
      "sf_wale": 1.0412275276366985,
      "sf_course": 1.040990950803262
    },
    {
      "region_id": 5,
      "row": 1,
      "col": 2,
      "knit_dir_deg": 0,
      "sf_wale": 1.0408540222418494,
      "sf_course": 1.0409635698729882
    },
    {
      "region_id": 6,
      "row": 2,
      "col": 0,
      "knit_dir_deg": 0,
      "sf_wale": 1.0417040275003855,
      "sf_course": 1.042349086961843
    },
    {
      "region_id": 7,
      "row": 2,
      "col": 1,
      "knit_dir_deg": 0,
      "sf_wale": 1.041686658090472,
      "sf_course": 1.0426926891667072
    },
    {
      "region_id": 8,
      "row": 2,
      "col": 2,
      "knit_dir_deg": 0,
      "sf_wale": 1.0415625386573628,
      "sf_course": 1.0412984971929873
    }
  ],
  "cables": [
    {
      "name": "A1",
      "rest_scale": 0.9942512520370098
    },
    {
      "name": "A2",
      "rest_scale": 0.9946367189934833
    },
    {
      "name": "A3",
      "rest_scale": 0.9963257340452285
    },
    {
      "name": "B1",
      "rest_scale": 0.9930392552686426
    },
    {
      "name": "B2",
      "rest_scale": 0.9933521303023874
    },
    {
      "name": "B3",
      "rest_scale": 0.9947013074385297
    },
    {
      "name": "C1",
      "rest_scale": 0.99144415791533
    },
    {
      "name": "C2",
      "rest_scale": 0.9907083783922874
    },
    {
      "name": "C3",
      "rest_scale": 0.9910637857000086
    },
    {
      "name": "D1",
      "rest_scale": 0.9944388169550606
    },
    {
      "name": "D2",
      "rest_scale": 0.9934462320266908
    },
    {
      "name": "D3",
      "rest_scale": 0.9936163241844805
    }
  ],
  "history": [
    {
      "call": 592,
      "loss": 0.0065311238540863275,
      "crown_height": 0.22111388
    },
    {
      "call": 593,
      "loss": 0.006713117263223932,
      "crown_height": 0.22056374
    },
    {
      "call": 594,
      "loss": 0.006648362921909877,
      "crown_height": 0.22123232
    },
    {
      "call": 595,
      "loss": 0.006299801887767623,
      "crown_height": 0.22156927
    },
    {
      "call": 596,
      "loss": 0.006570774097830909,
      "crown_height": 0.21932269
    },
    {
      "call": 597,
      "loss": 0.006850521265421398,
      "crown_height": 0.22209009
    },
    {
      "call": 598,
      "loss": 0.006432854498054829,
      "crown_height": 0.22111937
    },
    {
      "call": 599,
      "loss": 0.00636641443297511,
      "crown_height": 0.22089598
    },
    {
      "call": 600,
      "loss": 0.0064853602921847745,
      "crown_height": 0.221077
    },
    {
      "call": 601,
      "loss": 0.006470323101682706,
      "crown_height": 0.22044697
    },
    {
      "call": 602,
      "loss": 0.007647209281964263,
      "crown_height": 0.22161926
    },
    {
      "call": 603,
      "loss": 0.006992405395167315,
      "crown_height": 0.22061365
    },
    {
      "call": 604,
      "loss": 0.006461544046901121,
      "crown_height": 0.22059676
    },
    {
      "call": 605,
      "loss": 0.006936088917695169,
      "crown_height": 0.21707768
    },
    {
      "call": 606,
      "loss": 0.007035427276683359,
      "crown_height": 0.22049234
    },
    {
      "call": 607,
      "loss": 0.006475454255687377,
      "crown_height": 0.22042027
    },
    {
      "call": 608,
      "loss": 0.006755896706172681,
      "crown_height": 0.22021892
    },
    {
      "call": 609,
      "loss": 0.006991107949030683,
      "crown_height": 0.22020983
    },
    {
      "call": 610,
      "loss": 0.007996752938917127,
      "crown_height": 0.22439047
    },
    {
      "call": 611,
      "loss": 0.007868070610681184,
      "crown_height": 0.22149849
    },
    {
      "call": 612,
      "loss": 0.00716299462414111,
      "crown_height": 0.22355195
    },
    {
      "call": 613,
      "loss": 0.00856081603939181,
      "crown_height": 0.22465069
    },
    {
      "call": 614,
      "loss": 0.008353554743726732,
      "crown_height": 0.22200541
    },
    {
      "call": 615,
      "loss": 0.007827374150759214,
      "crown_height": 0.22412013
    },
    {
      "call": 616,
      "loss": 0.008872857065747638,
      "crown_height": 0.22738445
    },
    {
      "call": 617,
      "loss": 0.00907815118630982,
      "crown_height": 0.22643632
    },
    {
      "call": 618,
      "loss": 0.009138711866692763,
      "crown_height": 0.22761384
    },
    {
      "call": 619,
      "loss": 0.007702737055059406,
      "crown_height": 0.22714017
    },
    {
      "call": 620,
      "loss": 0.008048342729509468,
      "crown_height": 0.22649961
    },
    {
      "call": 621,
      "loss": 0.008155096289179155,
      "crown_height": 0.22757616
    }
  ]
}